ombot_utils/__init__.py
ombot_utils/callback_handler/__init__.py
ombot_utils/callback_handler/callback.py
ombot_utils/data_handler/__init__.py
ombot_utils/data_handler/base_sql_data_handler.py
ombot_utils/error_handler/__init__.py
ombot_utils/error_handler/error.py
ombot_utils/log_handler/__init__.py
ombot_utils/log_handler/logger.py
ombot_utils/schemas/__init__.py
ombot_utils/schemas/character.py
ombot_utils/schemas/event.py
ombot_utils/schemas/memory.py
ombot_utils/schemas/message.py
ombot_utils/schemas/opt.py
ombot_utils-0.0.2.dist-info/LICENSE
ombot_utils-0.0.2.dist-info/METADATA
ombot_utils-0.0.2.dist-info/WHEEL
ombot_utils-0.0.2.dist-info/top_level.txt
ombot_utils-0.0.2.dist-info/RECORD
