Metadata-Version: 2.1
Name: ombot-utils
Version: 0.0.2
Summary: Utils for OMbots
Author-email: panregedit <panregedit@gmail.com>
Project-URL: Homepage, https://git.linker.cc/research/misc/ombot_utils.git
Classifier: Programming Language :: Python :: 3
Classifier: License :: OSI Approved :: MIT License
Classifier: Operating System :: OS Independent
Requires-Python: >=3.7
License-File: LICENSE
